wtr_watcher.libs/libgcc_s-7393e603.so.1
wtr_watcher.libs/libstdc++-1b614e01.so.6.0.32
.wtr_watcher.mesonpy.libs/libwatcher-c.so.0.14.3
.wtr_watcher.mesonpy.libs/pkgconfig/watcher-c.pc
wtr_watcher-0.14.3.data/purelib/watcher.py
wtr_watcher-0.14.3.data/purelib/__init__.py
wtr_watcher-0.14.3.data/headers/wtr/watcher-c.h
wtr_watcher-0.14.3.dist-info/WHEEL
wtr_watcher-0.14.3.dist-info/license
wtr_watcher-0.14.3.dist-info/METADATA
wtr_watcher-0.14.3.dist-info/RECORD
