Metadata-Version: 2.1
Name: wtr-watcher
Version: 0.14.3
Summary: Filesystem watcher. Works anywhere. Simple, efficient, and friendly.
Keywords: watcher,filesystem,events,async
Author: Will
License: Copyright 2022 github.com/e-dant
